telegram_rss/__init__.py
telegram_rss/__main__.py
telegram_rss/commands/__init__.py
telegram_rss/commands/start.py
telegram_rss/commands/update.py
telegram_rss/config.py
telegram_rss/feed/__init__.py
telegram_rss/feed/channel.py
telegram_rss/feed/entry.py
telegram_rss/feed/feed.py
telegram_rss/feed/img.py
telegram_rss/feed/updater.py
telegram_rss/main.py
telegram_rss/telegram.py
telegram_rss/template.py
telegram_rss/utils.py
telegram_rss/version.py
telegram_rss-0.8.1.dist-info/entry_points.txt
telegram_rss-0.8.1.dist-info/LICENSE
telegram_rss-0.8.1.dist-info/WHEEL
telegram_rss-0.8.1.dist-info/METADATA
telegram_rss-0.8.1.dist-info/RECORD
