Metadata-Version: 2.1
Name: telegram-rss
Version: 0.8.1
Summary: Fetch rss and send the latest update to telegram.
Home-page: https://github.com/pentatester/telegram-rss
License: MIT
Author: hexatester
Author-email: hexatester@protonmail.com
Requires-Python: >=3.6.1,<4.0.0
Classifier: Development Status :: 4 - Beta
Classifier: Intended Audience :: Developers
Classifier: License :: OSI Approved :: MIT License
Classifier: Operating System :: OS Independent
Classifier: Programming Language :: Python
Classifier: Programming Language :: Python :: 3
Classifier: Programming Language :: Python :: 3.6
Classifier: Programming Language :: Python :: 3.7
Classifier: Programming Language :: Python :: 3.8
Classifier: Programming Language :: Python :: 3.9
Classifier: Topic :: Communications :: Chat
Requires-Dist: Jinja2 (>=2.11.3,<3.0.0)
Requires-Dist: attrs (>=20.3.0,<21.0.0)
Requires-Dist: beautifulsoup4 (>=4.9.3,<5.0.0)
Requires-Dist: bleach (>=3.2.3,<4.0.0)
Requires-Dist: click (>=7.1.2,<8.0.0)
Requires-Dist: feedparser (>=6.0.2,<7.0.0)
Requires-Dist: python-dateutil (>=2.8.1,<3.0.0)
Requires-Dist: python-telegram-bot (>=13.1,<14.0)
Requires-Dist: toml (>=0.10.2,<0.11.0)
Project-URL: Repository, https://github.com/pentatester/telegram-rss
